geospace/__init__.py
geospace/entropy.py
geospace/methods.py
geospace/cci/__init__.py
geospace/cci/cci.py
geospace/cci/cellchat.py
geospace/cci/spatial.py
geospace/data/__init__.py
geospace/data/data.py
geospace/data/database.py
geospace/hmrf/__init__.py
geospace/hmrf/hmrf.py
geospace/hmrf/hmrf_new.py
geospace/hotspot/__init__.py
geospace/hotspot/coexpression.py
geospace/hotspot/geometry.py
geospace/hotspot/hotspot.py
geospace/hotspot/interaction_hotspot.py
geospace/plot/__init__.py
geospace/plot/hotspots.py
geospace/plot/plot.py
geospace/plot/tracksplot.py
geospace/utility/__init__.py
geospace/utility/utility.py
geospace_st-1.0.0.dist-info/LICENSE
geospace_st-1.0.0.dist-info/METADATA
geospace_st-1.0.0.dist-info/WHEEL
geospace_st-1.0.0.dist-info/top_level.txt
geospace_st-1.0.0.dist-info/RECORD
